somfy_rts/__init__.py
somfy_rts/rts.py
somfy_rts-1.1.0.dist-info/LICENSE.txt
somfy_rts-1.1.0.dist-info/METADATA
somfy_rts-1.1.0.dist-info/WHEEL
somfy_rts-1.1.0.dist-info/top_level.txt
somfy_rts-1.1.0.dist-info/RECORD
